AfdianBot/__init__.py
AfdianBot/bot.py
AfdianBot/config.py
AfdianBot/exceptions.py
AfdianBot/utils/__init__.py
AfdianBot/utils/api.py
AfdianBot/utils/bot_vars.py
AfdianBot/utils/constant.py
AfdianBot/utils/ctx.py
AfdianBot/utils/types.py
AfdianBot-1.0.4.dist-info/LICENSE
AfdianBot-1.0.4.dist-info/METADATA
AfdianBot-1.0.4.dist-info/WHEEL
AfdianBot-1.0.4.dist-info/top_level.txt
AfdianBot-1.0.4.dist-info/RECORD
