Metadata-Version: 2.1
Name: AfdianBot
Version: 1.0.4
Summary: 爱发电Bot SDK
Author: sun589
Author-email: goodluck1787@outlook.com
Classifier: Programming Language :: Python :: 3
Classifier: License :: OSI Approved :: MIT License
Classifier: Operating System :: OS Independent
Requires-Python: >=3.7
License-File: LICENSE
Requires-Dist: requests>=2.32.2
Requires-Dist: fake-useragent>=2.0.3
